timepicker_control/__init__.py
timepicker_control/timepicker.py
timepicker_control/wheel_column.py
timepicker_control-1.0.9.dist-info/LICENSE
timepicker_control-1.0.9.dist-info/METADATA
timepicker_control-1.0.9.dist-info/WHEEL
timepicker_control-1.0.9.dist-info/top_level.txt
timepicker_control-1.0.9.dist-info/RECORD
