Metadata-Version: 2.2
Name: timepicker_control
Version: 1.0.9
Summary: A modern, customizable time picker widget for PySide6 with default time settings, minute intervals, and theme support
Author-email: Next Wave Tech Solutions <info@nextwavetechsolutions.com>
License: MIT
Project-URL: Homepage, https://github.com/nextwavetchsolutions/timepicker_control
Project-URL: Bug Tracker, https://github.com/nextwavetchsolutions/timepicker_control/issues
Project-URL: Documentation, https://github.com/nextwavetchsolutions/timepicker_control#readme
Keywords: pyside6,qt,timepicker,widget,gui,time,picker,settings,theme,customizable
Classifier: Programming Language :: Python :: 3
Classifier: License :: OSI Approved :: MIT License
Classifier: Operating System :: OS Independent
Classifier: Development Status :: 5 - Production/Stable
Classifier: Intended Audience :: Developers
Classifier: Topic :: Software Development :: Libraries :: Python Modules
Classifier: Topic :: Software Development :: User Interfaces
Requires-Python: >=3.7
License-File: LICENSE
Requires-Dist: PySide6>=6.0.0
